Metadata-Version: 2.1
Name: avln
Version: 1.0.0
Summary: namespace package for avalon project in yashihq.com
Home-page: UNKNOWN
Author: Qiangning Hong
Author-email: hongqn@yashihq.com
License: MIT
Platform: UNKNOWN
Requires-Python: >=3.3
Provides-Extra: dev
